{
  "site": "cardsnap",
  "dataType": "grade-or-skip",
  "stagedAt": "2026-04-14T00:27:51.949Z",
  "entries": [
    {
      "slug": "football",
      "sport": "Football",
      "category": "football",
      "seoTitle": "Football Card Grading ROI Guide — When to Grade | CardSnap",
      "seoDescription": "Should grade-or-skip Football cards? See ROI by condition/era/player.",
      "h1": "Should You Grade Your Football Card?",
      "subtitle": "This guide helps Football card collectors determine when to grade their cards for maximum ROI. Explore the factors influencing grading decisions tailored to Football cards.",
      "gradingLogic": [
        "High-value rookie cards from star players are often worth grading due to their potential market demand.",
        "Limited edition or short print cards can significantly appreciate in value when graded, especially in pristine condition.",
        "Vintage Football cards from the 1980s and 1990s can see substantial ROI when graded, particularly if they are in high grade.",
        "Autographed Football cards increase in desirability and value when graded, especially if they are authenticated.",
        "Cards from recent Super Bowl MVPs or Hall of Famers often yield better returns when graded, reflecting their popularity."
      ],
      "keyCharacteristics": [
        {
          "title": "Centering",
          "desc": "Proper centering is crucial for Football cards, as it greatly affects the overall grade and market value."
        },
        {
          "title": "Corners",
          "desc": "Sharp corners are essential for grading; any wear can drastically lower the card's value."
        },
        {
          "title": "Surface Quality",
          "desc": "Scratches or blemishes on the surface can diminish a Football card's grade and appeal."
        },
        {
          "title": "Edges",
          "desc": "Clean, undamaged edges are vital for achieving higher grades, influencing potential resale values."
        }
      ],
      "roiExamples": [
        {
          "cardName": "2020 Justin Herbert Prizm Rookie Card",
          "rawValue": 100,
          "psa9Value": 400,
          "psa10Value": 1200,
          "gradingCost": 50,
          "psa9Roi": 250,
          "psa10Roi": 1050,
          "verdict": "strong",
          "reason": "This card has high demand due to Herbert's performance and potential, making grading a lucrative option."
        },
        {
          "cardName": "2018 Baker Mayfield Donruss Rated Rookie",
          "rawValue": 30,
          "psa9Value": 80,
          "psa10Value": 200,
          "gradingCost": 50,
          "psa9Roi": 0,
          "psa10Roi": 120,
          "verdict": "moderate",
          "reason": "While this card has some value, the grading cost reduces the ROI potential significantly."
        },
        {
          "cardName": "2019 Panini Score Base Card",
          "rawValue": 5,
          "psa9Value": 15,
          "psa10Value": 40,
          "gradingCost": 50,
          "psa9Roi": -40,
          "psa10Roi": -15,
          "verdict": "skip",
          "reason": "The low value of this common card makes grading financially unviable."
        }
      ],
      "whenToGrade": [
        "When you possess a high-demand rookie card from a current star player.",
        "If you have a limited edition card that is in excellent condition.",
        "For vintage Football cards that are well-preserved and have a strong collector interest.",
        "When you own autographed cards that can be authenticated and graded.",
        "If your card features a player who has recently achieved significant accolades, such as a Super Bowl MVP."
      ],
      "skipGrading": [
        "When the card is a common base card with little market interest.",
        "If the card is in poor condition with visible wear and tear.",
        "For cards that are not from a recognized brand or set.",
        "When the grading fees exceed the potential market value of the card."
      ],
      "marketInsight": "The Football card market has seen a resurgence, with increased demand for both vintage and modern cards. Grading can significantly impact ROI, especially for high-profile players, but collectors should be discerning about which cards to submit.",
      "schema_jsonld": {
        "@context": "https://schema.org",
        "@graph": [
          {
            "@type": "Article",
            "headline": "Football Card Grading ROI Guide — When to Grade | CardSnap",
            "description": "Should grade-or-skip Football cards? See ROI by condition/era/player.",
            "url": "https://cardsnap.io/grade-or-skip/football",
            "author": {
              "@type": "Organization",
              "name": "CardSnap"
            },
            "publisher": {
              "@type": "Organization",
              "name": "CardSnap"
            }
          },
          {
            "@type": "BreadcrumbList",
            "itemListElement": [
              {
                "@type": "ListItem",
                "position": 1,
                "name": "Home",
                "item": "https://cardsnap.io"
              },
              {
                "@type": "ListItem",
                "position": 2,
                "name": "Grade or Skip",
                "item": "https://cardsnap.io/grade-or-skip"
              },
              {
                "@type": "ListItem",
                "position": 3,
                "name": "Football Cards"
              }
            ]
          }
        ]
      },
      "_meta": {
        "generated_at": "2026-04-10T19:01:43.237Z",
        "source": "cardsnap-generator",
        "review_status": "pending"
      }
    }
  ],
  "conflicts": [],
  "metadata": {
    "sourceFile": "grade-or-skip-2026-04-10T19-05-05.json",
    "strategy": "skip"
  }
}